odoo/addons/base_warn_option/README.rst
odoo/addons/base_warn_option/__init__.py
odoo/addons/base_warn_option/__manifest__.py
odoo/addons/base_warn_option/i18n/base_warn_option.pot
odoo/addons/base_warn_option/i18n/es.po
odoo/addons/base_warn_option/i18n/it.po
odoo/addons/base_warn_option/models/__init__.py
odoo/addons/base_warn_option/models/warn_option.py
odoo/addons/base_warn_option/readme/CONTEXT.md
odoo/addons/base_warn_option/readme/CONTRIBUTORS.md
odoo/addons/base_warn_option/readme/DESCRIPTION.md
odoo/addons/base_warn_option/security/ir.model.access.csv
odoo/addons/base_warn_option/static/description/icon.png
odoo/addons/base_warn_option/static/description/index.html
odoo/addons/base_warn_option/views/res_config_settings_views.xml
odoo/addons/base_warn_option/views/warn_option_views.xml
odoo_addon_base_warn_option-18.0.1.0.0.5.dist-info/METADATA
odoo_addon_base_warn_option-18.0.1.0.0.5.dist-info/WHEEL
odoo_addon_base_warn_option-18.0.1.0.0.5.dist-info/top_level.txt
odoo_addon_base_warn_option-18.0.1.0.0.5.dist-info/RECORD
